{
  "allOf": [
    {
      "$ref": "./errorBase.json"
    }
  ],
  "type": "object",
  "properties": {
    "status": {
      "type": "integer",
      "enum": [403]
    },
    "description": {
      "type": "string",
      "enum": ["Forbidden"]
    },
    "cause": {
      "type": "object",
      "properties": {
        "kind": {
          "type": "string",
          "enum": [
            "CsrfTokenRequired",
            "CsrfHeaderRequired",
            "InvalidOrigin"
          ]
        }
      },
      "required": [
        "kind"
      ]
    }
  },
  "required": [
    "status",
    "description"
  ]
}
